ldap_tools/__init__.py
ldap_tools/audit.py
ldap_tools/client.py
ldap_tools/commands.py
ldap_tools/exceptions.py
ldap_tools/group.py
ldap_tools/key.py
ldap_tools/user.py
ldap_tools-0.7.12.dist-info/METADATA
ldap_tools-0.7.12.dist-info/RECORD
ldap_tools-0.7.12.dist-info/WHEEL
ldap_tools-0.7.12.dist-info/entry_points.txt
ldap_tools-0.7.12.dist-info/top_level.txt
