Metadata-Version: 2.1
Name: ldap-tools
Version: 0.7.12
Summary: A set of tools to make managing LDAP users, groups, and keys easier
Home-page: https://github.com/carta/ldap_tools
Author: Ali Tayarani
Author-email: ali.tayarani@carta.com
License: MIT
Platform: UNKNOWN
Classifier: Development Status :: 3 - Alpha
Classifier: Intended Audience :: Developers
Classifier: Intended Audience :: Information Technology
Classifier: Intended Audience :: System Administrators
Classifier: License :: OSI Approved :: MIT License
Classifier: Natural Language :: English
Classifier: Operating System :: MacOS :: MacOS X
Classifier: Operating System :: POSIX :: Linux
Classifier: Programming Language :: Python
Classifier: Programming Language :: Python :: 3.5
Classifier: Topic :: System :: Systems Administration :: Authentication/Directory :: LDAP
Classifier: Topic :: Utilities
Requires-Dist: ldap3
Requires-Dist: click
Requires-Dist: sshpubkeys
Requires-Dist: pyyaml
